bitscreen_cli/__init__.py
bitscreen_cli/__main__.py
bitscreen_cli/commands/__init__.py
bitscreen_cli/commands/auth.py
bitscreen_cli/commands/cid.py
bitscreen_cli/commands/dashboard.py
bitscreen_cli/commands/directory.py
bitscreen_cli/commands/filter.py
bitscreen_cli/commands/settings.py
bitscreen_cli/commands/setup.py
bitscreen_cli-0.1.25.dist-info/METADATA
bitscreen_cli-0.1.25.dist-info/WHEEL
bitscreen_cli-0.1.25.dist-info/dependency_links.txt
bitscreen_cli-0.1.25.dist-info/entry_points.txt
bitscreen_cli-0.1.25.dist-info/top_level.txt
bitscreen_cli-0.1.25.dist-info/RECORD
