Metadata-Version: 2.1
Name: bitscreen-cli
Version: 0.1.25
Summary: CLI client for BitScreen
Home-page: UNKNOWN
Author: Keyko
License: UNKNOWN
Platform: UNKNOWN
Classifier: License :: OSI Approved :: MIT License
Classifier: Programming Language :: Python :: 3
Classifier: Programming Language :: Python :: 3.9
Requires-Python: >=3.0
Requires-Dist: dashing ==0.1.0
Requires-Dist: py-crypto-hd-wallet ==0.13.0
Requires-Dist: requests ==2.26.0
Requires-Dist: tabulate ==0.8.9
Requires-Dist: typer ==0.4.1
Requires-Dist: web3 ==5.23.1
